pyliter/__init__.py
pyliter/__main__.py
pyliter/__version__.py
pyliter/document.py
pyliter/render.py
pyliter/resources/2016-lite_style.yaml
pyliter/resources/2016_style.yaml
pyliter/resources/2016a-lite_style.yaml
pyliter/resources/2016a_style.yaml
pyliter/resources/2016b-lite_style.yaml
pyliter/resources/2016b_style.yaml
pyliter/resources/2017-lite_style.yaml
pyliter/resources/2017_style.yaml
pyliter/resources/2017a-lite_style.yaml
pyliter/resources/2017a_style.yaml
pyliter/resources/2018-lite_style.yaml
pyliter/resources/2018_style.yaml
pyliter/resources/2019-lite_style.yaml
pyliter/resources/2019_style.yaml
pyliter/resources/2019a-lite_style.yaml
pyliter/resources/2019a_style.yaml
pyliter/resources/__init__.py
pyliter/resources/beach-lite_style.yaml
pyliter/resources/beach_style.yaml
pyliter/resources/camo0-lite_style.yaml
pyliter/resources/camo0_style.yaml
pyliter/resources/camo1-lite_style.yaml
pyliter/resources/camo1_style.yaml
pyliter/resources/crayola_bright.yaml
pyliter/resources/crayola_colors.yaml
pyliter/resources/crayola_fluorescent.yaml
pyliter/resources/crayola_fragrance.yaml
pyliter/resources/crayola_jewelry.yaml
pyliter/resources/crayola_magic.yaml
pyliter/resources/crayola_metallic.yaml
pyliter/resources/crayola_scary.yaml
pyliter/resources/crayola_silver.yaml
pyliter/resources/css_colors.yaml
pyliter/resources/default_style.yaml
pyliter/resources/flower-lite_style.yaml
pyliter/resources/flower_style.yaml
pyliter/resources/highway-lite_style.yaml
pyliter/resources/highway_style.yaml
pyliter/resources/rustic0_style.yaml
pyliter/resources/rustic1_style.yaml
pyliter/resources/rustic2_style.yaml
pyliter/resources/safety-lite_style.yaml
pyliter/resources/safety_style.yaml
pyliter/resources/sand-lite_style.yaml
pyliter/resources/sand_style.yaml
pyliter/resources/sky-lite_style.yaml
pyliter/resources/sky_style.yaml
pyliter/style_book.py
pyliter/token.py
pyliter-1.5.0.dist-info/entry_points.txt
pyliter-1.5.0.dist-info/LICENSE
pyliter-1.5.0.dist-info/WHEEL
pyliter-1.5.0.dist-info/METADATA
pyliter-1.5.0.dist-info/RECORD
