Metadata-Version: 2.1
Name: pyliter
Version: 1.5.0
Summary: Generate color syntax highlighted PNG image from python source files.
Home-page: https://github.com/JnyJny/pyliter
License: Apache-2.0
Author: jnyjny
Author-email: erik.oshaughnessy@gmail.com
Requires-Python: >=3.7,<4.0
Classifier: License :: OSI Approved :: Apache Software License
Classifier: Programming Language :: Python :: 3
Classifier: Programming Language :: Python :: 3.7
Classifier: Programming Language :: Python :: 3.8
Classifier: Programming Language :: Python :: 3.9
Requires-Dist: click (>=7.0,<8.0)
Requires-Dist: pyglet (>=1.4.8,<2.0.0)
Requires-Dist: pyyaml (>=5.2,<6.0)
Requires-Dist: typer (>=0.3.2,<0.4.0)
Requires-Dist: webcolors (>=1.11.1,<2.0.0)
Project-URL: Documentation, https://github.com/JnyJny/pyliter
Project-URL: Repository, https://github.com/JnyJny/pyliter
